CHANGELOG.md
MANIFEST.in
README.md
setup.py
pylibcklb/ClassLibrary.py
pylibcklb/FunctionLibrary.py
pylibcklb/__init__.py
pylibcklb/metadata.py
pylibcklb/version.py
pylibcklb.egg-info/PKG-INFO
pylibcklb.egg-info/SOURCES.txt
pylibcklb.egg-info/dependency_links.txt
pylibcklb.egg-info/not-zip-safe
pylibcklb.egg-info/requires.txt
pylibcklb.egg-info/top_level.txt
pylibcklb/administration/__init__.py
pylibcklb/administration/admin.py
pylibcklb/database/__init__.py
pylibcklb/database/sqlite3_functions.py
pylibcklb/installer/__init__.py
pylibcklb/installer/pyinstaller.py
pylibcklb/math/__init__.py
pylibcklb/math/math_functions.py
pylibcklb/ontology/__init__.py
pylibcklb/ontology/classes.py
pylibcklb/ontology/functions.py
pylibcklb/opencv34/__init__.py
pylibcklb/opencv34/functions.py
pylibcklb/pyqt5/__init__.py
pylibcklb/pyqt5/classes.py
pylibcklb/pyqt5/functions.py
pylibcklb/visualization/__init__.py
pylibcklb/visualization/images/__init__.py
pylibcklb/visualization/images/classes.py
pylibcklb/visualization/plot/__init__.py
pylibcklb/visualization/plot/functions.py
pylibcklb/xml/__init__.py
pylibcklb/xml/lxml_functions.py