Metadata-Version: 2.1
Name: pylibcklb
Version: 1.10.0
Summary: The pylibcklb is a library of functions and classes created from me and were used in different other projects of me.
Home-page: https://github.com/ecklebe/pylibcklb
Author: Tobias Ecklebe
Author-email: development.ecklebe@outlook.de
License: GNU LGPLv3
Download-URL: https://github.com/ecklebe/pylibcklb/archive/master.zip
Platform: UNKNOWN
Classifier: Natural Language :: English
Classifier: Programming Language :: Python :: 3.6
Classifier: License :: OSI Approved :: GNU Lesser General Public License v3 (LGPLv3)
Classifier: Operating System :: Microsoft :: Windows :: Windows 10
Classifier: Topic :: Software Development :: Libraries
Requires-Python: >=3
Provides-Extra: gui
